{
    "name": { "ascii": "Complex numbers", "ru_RU": "Комплексные числа" },
    "types": [
        {
            "name": { "ascii": "complex", "ru_RU": "компл" },
            "fields": [
				{ "name": "re", "baseType": "double" },
				{ "name": "im", "baseType": "double" }
			]
        }
    ],
	"methods": [
        {
            "name": {"ascii": "Re" },
            "returnType": "double",
            "arguments": [
                { "name": "x", "baseType": "complex" }
            ]
        },
        {
            "name": {"ascii": "Im" },
            "returnType": "double",
            "arguments": [
                { "name": "x", "baseType": "complex" }
            ]
        },
        {
            "name": {"ascii": "+" },
            "returnType": "complex",
            "arguments": [
                { "name": "x", "baseType": "complex" },
                { "name": "y", "baseType": "complex" }
            ]
        },
        {
            "name": {"ascii": "-" },
            "returnType": "complex",
            "arguments": [
                { "name": "x", "baseType": "complex" },
                { "name": "y", "baseType": "complex" }
            ]
        },
        {
            "name": {"ascii": "*" },
            "returnType": "complex",
            "arguments": [
                { "name": "x", "baseType": "complex" },
                { "name": "y", "baseType": "complex" }
            ]
        },
        {
            "name": {"ascii": "/" },
            "returnType": "complex",
            "arguments": [
                { "name": "x", "baseType": "complex" },
                { "name": "y", "baseType": "complex" }
            ]
        },
		{
			"name": ":=",
			"returnType": "complex",
			"arguments": [
				{ "name": "x", "baseType": "int" }
			]
		},
		{
			"name": ":=",
			"returnType": "complex",
			"arguments": [
				{ "name": "x", "baseType": "double" }
			]
		},
		{
			"name": { "ascii": "input", "ru_RU": "ввод" },
			"returnType": "complex",
			"arguments": [
				{ "name": "x", "baseType": "string" },
				{ "name": "ok", "baseType": "bool", "access": "out"}
			]
		},
		{
			"name": { "ascii": "output", "ru_RU": "вывод" },
			"returnType": "string",
			"arguments": [
				{ "name": "x", "baseType": "complex" }
			]
		}
    ]
}
